brain_games/__init__.py
brain_games/cli.py
brain_games/games/brain_calc.py
brain_games/games/brain_even.py
brain_games/games/brain_gcd.py
brain_games/games/brain_is_prime.py
brain_games/games/brain_progression.py
brain_games/scripts/__init__.py
brain_games/scripts/brain_calc.py
brain_games/scripts/brain_even.py
brain_games/scripts/brain_games.py
brain_games/scripts/brain_gcd.py
brain_games/scripts/brain_is_prime.py
brain_games/scripts/brain_progression.py
brain_games_by_ms-0.1.0.dist-info/entry_points.txt
brain_games_by_ms-0.1.0.dist-info/WHEEL
brain_games_by_ms-0.1.0.dist-info/METADATA
brain_games_by_ms-0.1.0.dist-info/RECORD
